[{"json_dict": null, "banned_by": null, "subreddit_id": "t5_2ucq2", "subreddit": "cleanjokes", "selftext_html": "<!-- SC_OFF --><div class=\"md\"><p>&quot;Rhino horn?&quot;</p>\n</div><!-- SC_ON -->", "selftext": "\"Rhino horn?\"", "likes": null, "suggested_sort": null, "user_reports": [], "link_flair_text": null, "gilded": 0, "archived": true, "clicked": false, "title": "What did the elephant say to the horn-less rhino?", "_has_fetched": true, "_comment_sort": null, "_replaced_more": false, "over_18": false, "hidden": false, "hide_score": false, "link_flair_css_class": null, "_info_url": "https://api.reddit.com/api/info/", "downs": 0, "saved": false, "removal_reason": null, "from_id": null, "locked": false, "name": "t3_2decug", "author_flair_text": null, "quarantine": false, "visited": false, "num_reports": null, "distinguished": null, "domain": "self.cleanjokes", "_comments_by_id": {}, "_api_link": "https://api.reddit.com/r/cleanjokes/comments/2decug/what_did_the_elephant_say_to_the_hornless_rhino/?ref=search_posts", "media_embed": {}, "secure_media": null, "id": "2decug", "from_kind": null, "secure_media_embed": {}, "report_reasons": null, "author": "Seanofthebread112", "media": null, "_orphaned": {}, "score": 31, "approved_by": null, "_uniq": null, "thumbnail": "", "edited": false, "author_flair_css_class": null, "reddit_session": "Unauthenticated reddit session", "mod_reports": [], "from": null, "is_self": true, "_comments": null, "_params": {}, "_underscore_names": null, "permalink": "https://www.reddit.com/r/cleanjokes/comments/2decug/what_did_the_elephant_say_to_the_hornless_rhino/?ref=search_posts", "stickied": false, "created": 1407925888.0, "url": "https://www.reddit.com/r/cleanjokes/comments/2decug/what_did_the_elephant_say_to_the_hornless_rhino/", "created_utc": 1407897088.0, "ups": 31, "num_comments": 4}]